musiio_validate_tsv/__init__.py
musiio_validate_tsv/exceptions.py
musiio_validate_tsv/utils.py
musiio_validate_tsv/validate_tsv.py
musiio_validate_tsv-1.0.2.dist-info/LICENSE.txt
musiio_validate_tsv-1.0.2.dist-info/METADATA
musiio_validate_tsv-1.0.2.dist-info/WHEEL
musiio_validate_tsv-1.0.2.dist-info/top_level.txt
musiio_validate_tsv-1.0.2.dist-info/RECORD
