Metadata-Version: 2.1
Name: musiio_validate_tsv
Version: 1.0.2
Summary: A library for validating tsv files before uploading them to the Musiio API
Home-page: https://bitbucket.org/musiio/musiio-validate-tsv
Author: vignesh
Author-email: vignesh@musiio.com
License: MIT License
Platform: UNKNOWN
Classifier: Programming Language :: Python :: 3
Classifier: License :: OSI Approved :: MIT License
Classifier: Operating System :: OS Independent
Requires-Python: >=3.6
License-File: LICENSE.txt
